altan/__init__.py
altan/exceptions.py
altan/agents/__init__.py
altan/agents/agent.py
altan/agents/agents/__init__.py
altan/agents/agents/activations.py
altan/agents/agents/base_client.py
altan/agents/agents/beta_features.py
altan/agents/agents/client.py
altan/agents/agents/errors.py
altan/agents/agents/event_types.py
altan/agents/agents/history.py
altan/agents/agents/hooks.py
altan/agents/agents/managed_types.py
altan/agents/agents/py.typed
altan/agents/agents/rate_limiter.py
altan/agents/agents/responses.py
altan/agents/agents/stream_manager.py
altan/agents/agents/streaming_helpers.py
altan/agents/agents/sync_client.py
altan/agents/agents/tools.py
altan/agents/agents/types.py
altan/agents/agents/usage_tracker.py
altan/agents/agents/validation.py
altan/agents/examples/__init__.py
altan/agents/examples/activations_basic.py
altan/agents/examples/activations_streaming.py
altan/agents/examples/message_formats_demo.py
altan/agents/examples/responses_basic.py
altan/agents/examples/responses_streaming.py
altan/agents/examples/cookbooks/00_api_comparison.py
altan/agents/examples/cookbooks/01_basic_chat.py
altan/agents/examples/cookbooks/01_basic_chat_managed.py
altan/agents/examples/cookbooks/02_function_calling.py
altan/agents/examples/cookbooks/02_function_calling_managed.py
altan/agents/examples/cookbooks/03_customer_support_bot.py
altan/agents/examples/cookbooks/03b_rich_message_format.py
altan/agents/examples/cookbooks/04_multi_agent_collaboration.py
altan/agents/examples/cookbooks/05_multi_user_conversations.py
altan/agents/examples/cookbooks/06_code_assistant.py
altan/agents/examples/cookbooks/07_web_search.py
altan/agents/examples/cookbooks/08_deep_research_anthropic.py
altan/agents/examples/cookbooks/09_deep_research_openai.py
altan/agents/examples/cookbooks/09_parallel_requests.py
altan/agents/examples/cookbooks/10_advanced_streaming.py
altan/agents/examples/cookbooks/run_cookbooks.py
altan/agents/examples/cookbooks/utils/__init__.py
altan-0.3.0.dist-info/licenses/LICENSE
altan-0.3.0.dist-info/METADATA
altan-0.3.0.dist-info/WHEEL
altan-0.3.0.dist-info/top_level.txt
altan-0.3.0.dist-info/RECORD
