Metadata-Version: 2.4
Name: altan
Version: 0.3.0
Summary: Python SDK for Altan API - AI Agents and 5000+ platform integrations
Home-page: https://github.com/altan/altan-sdk
Author: Altan
Author-email: Altan <support@altan.ai>
License-Expression: MIT
Project-URL: Homepage, https://altan.ai
Project-URL: Documentation, https://github.com/altan/altan-sdk#readme
Project-URL: Repository, https://github.com/altan/altan-sdk
Project-URL: Issues, https://github.com/altan/altan-sdk/issues
Keywords: altan,api,sdk,integration,automation,database,postgrest,supabase
Classifier: Development Status :: 3 - Alpha
Classifier: Intended Audience :: Developers
Classifier: Operating System :: OS Independent
Classifier: Programming Language :: Python :: 3
Classifier: Programming Language :: Python :: 3 :: Only
Classifier: Programming Language :: Python :: 3.8
Classifier: Programming Language :: Python :: 3.9
Classifier: Programming Language :: Python :: 3.10
Classifier: Programming Language :: Python :: 3.11
Requires-Python: >=3.8
License-File: LICENSE
Requires-Dist: httpx>=0.24.0
Requires-Dist: pydantic>=2.0.0
Requires-Dist: typing-extensions>=4.0.0
Dynamic: author
Dynamic: home-page
Dynamic: license-file
Dynamic: requires-python
